fluster/__init__.py
fluster/cluster.py
fluster/exceptions.py
fluster/penalty_box.py
fluster/utils.py
fluster/__pycache__/__init__.cpython-35.pyc
fluster/__pycache__/__init__.cpython-36.pyc
fluster/__pycache__/__init__.cpython-37.pyc
fluster/__pycache__/cluster.cpython-35.pyc
fluster/__pycache__/cluster.cpython-36.pyc
fluster/__pycache__/cluster.cpython-37.pyc
fluster/__pycache__/exceptions.cpython-35.pyc
fluster/__pycache__/exceptions.cpython-36.pyc
fluster/__pycache__/exceptions.cpython-37.pyc
fluster/__pycache__/penalty_box.cpython-35.pyc
fluster/__pycache__/penalty_box.cpython-36.pyc
fluster/__pycache__/penalty_box.cpython-37.pyc
fluster/__pycache__/utils.cpython-37.pyc
tests/__init__.py
tests/fluster/__init__.py
tests/fluster/test_cluster.py
tests/fluster/test_penalty_box.py
tests/fluster/test_utils.py
fluster-0.1.1.dist-info/LICENSE
fluster-0.1.1.dist-info/METADATA
fluster-0.1.1.dist-info/WHEEL
fluster-0.1.1.dist-info/top_level.txt
fluster-0.1.1.dist-info/zip-safe
fluster-0.1.1.dist-info/RECORD
